{
    "version": 1,
    "work": "sheet_music_01",
    "source": {
        "layer": "measures",
        "path": "measures/page_003/staff_004/measure_007.jpg"
    },
    "items": [
        {
            "index": 1,
            "name": "note_001",
            "position": {
                "top": 0,
                "left": 16,
                "width": 55,
                "height": 128
            }
        },
        {
            "index": 2,
            "name": "note_002",
            "position": {
                "top": 2,
                "left": 239,
                "width": 52,
                "height": 121
            }
        }
    ],
    "item_layer": "notes"
}
